LICENSE
MANIFEST.in
README.md
setup.cfg
setup.py
tap_gocardless/__init__.py
tap_gocardless/client.py
tap_gocardless/discover.py
tap_gocardless/schema.py
tap_gocardless/sync.py
tap_gocardless/transform.py
tap_gocardless.egg-info/PKG-INFO
tap_gocardless.egg-info/SOURCES.txt
tap_gocardless.egg-info/dependency_links.txt
tap_gocardless.egg-info/entry_points.txt
tap_gocardless.egg-info/requires.txt
tap_gocardless.egg-info/top_level.txt
tap_gocardless/schemas/events.json
tap_gocardless/schemas/payments.json
tap_gocardless/schemas/payout_items.json
tap_gocardless/schemas/payouts.json